lz/__init__.py
lz/filtration.py
lz/functional.py
lz/iterating.py
lz/left.py
lz/logical.py
lz/py.typed
lz/replication.py
lz/reversal.py
lz/right.py
lz/transposition.py
lz/typology.py
lz/_core/__init__.py
lz/_core/arithmetical.py
lz/_core/functional.py
lz/_core/left.py
lz/_core/right.py
lz/_core/signatures.py
lz/_core/textual.py
lz-3.0.0.dist-info/LICENSE
lz-3.0.0.dist-info/METADATA
lz-3.0.0.dist-info/WHEEL
lz-3.0.0.dist-info/top_level.txt
lz-3.0.0.dist-info/RECORD
