Metadata-Version: 2.1
Name: lz
Version: 3.0.0
Summary: Functional utilities.
Home-page: https://github.com/lycantropos/lz/
Download-URL: https://github.com/lycantropos/lz/archive/master.zip
Author: Azat Ibrakov
Author-email: azatibrakov@gmail.com
License: MIT License
Classifier: License :: OSI Approved :: MIT License
Classifier: Programming Language :: Python :: 3.7
Classifier: Programming Language :: Python :: 3.8
Classifier: Programming Language :: Python :: 3.9
Classifier: Programming Language :: Python :: 3.10
Classifier: Programming Language :: Python :: Implementation :: CPython
Classifier: Programming Language :: Python :: Implementation :: PyPy
Requires-Python: >=3.7
License-File: LICENSE
Requires-Dist: paradigm (<5.0,>=4.0.0)
Requires-Dist: reprit (<1.0,>=0.8.0)
Requires-Dist: typing-extensions (<5.0,>=4.4.0)
